docs/Makefile
docs/build/html/_downloads/91bb565024158a56df96d4b38072d9cb/spgl1s.py
docs/build/html/_downloads/bba121d488a5bad3f2af88bcdd090292/mmvnn.py
docs/source/conf.py
docs/source/credits.rst
docs/source/index.rst
docs/source/installation.rst
docs/source/_static/pylops.png
docs/source/_static/pylops_b.png
docs/source/_static/style.css
docs/source/_templates/breadcrumbs.html
docs/source/_templates/layout.html
docs/source/_templates/autosummary/base.rst
docs/source/_templates/autosummary/class.rst
docs/source/_templates/autosummary/exception.rst
docs/source/_templates/autosummary/function.rst
docs/source/_templates/autosummary/module.rst
docs/source/api/index.rst
docs/source/tutorials/mmvnn.py
docs/source/tutorials/spgl1s.py
examples/Official_demo.ipynb
spgl1/__init__.py
spgl1/lsqr.py
spgl1/spgl1.py
spgl1/version.py
testdata/mmvnn.npz
tutorials/README.txt
tutorials/mmvnn.py
tutorials/spgl1s.py
spgl1-0.0.3.dist-info/METADATA
spgl1-0.0.3.dist-info/WHEEL
spgl1-0.0.3.dist-info/top_level.txt
spgl1-0.0.3.dist-info/RECORD
