Metadata-Version: 2.1
Name: spgl1
Version: 0.0.3
Summary: SPGL1: A solver for large-scale sparse reconstruction.
Author-email: David Relyea <drrelyea@gmail.com>, Matteo Ravasi <matteoravasi@gmail.com>
License: GNU LESSER GENERAL PUBLIC LICENSE
Keywords: algebra,inverse problems,large-scale optimization
Classifier: Development Status :: 5 - Production/Stable
Classifier: Intended Audience :: Developers
Classifier: Intended Audience :: Science/Research
Classifier: Intended Audience :: Education
Classifier: License :: OSI Approved :: GNU Lesser General Public License v3 (LGPLv3)
Classifier: Natural Language :: English
Classifier: Operating System :: OS Independent
Classifier: Programming Language :: Python :: 3 :: Only
Classifier: Programming Language :: Python :: 3.9
Classifier: Programming Language :: Python :: 3.10
Classifier: Programming Language :: Python :: 3.11
Classifier: Topic :: Scientific/Engineering :: Mathematics
Requires-Dist: numpy>=1.15.0
Requires-Dist: scipy
